stock_data_loader/__init__.py
stock_data_loader/loader.py
stock_data_loader-0.1.4.dist-info/METADATA
stock_data_loader-0.1.4.dist-info/WHEEL
stock_data_loader-0.1.4.dist-info/top_level.txt
stock_data_loader-0.1.4.dist-info/RECORD
