Metadata-Version: 2.1
Name: stock-data-loader
Version: 0.1.4
Summary: A Python library for loading stock data from the Seeking Alpha API
Home-page: https://github.com/patzen123/stock-data-loader
Author: Patrick Ashrafi
Author-email: pa@ai-holding.com
Classifier: Development Status :: 3 - Alpha
Classifier: Intended Audience :: Developers
Classifier: License :: OSI Approved :: MIT License
Classifier: Operating System :: OS Independent
Classifier: Programming Language :: Python :: 3
Classifier: Programming Language :: Python :: 3.6
Classifier: Programming Language :: Python :: 3.7
Classifier: Programming Language :: Python :: 3.8
Classifier: Programming Language :: Python :: 3.9
Requires-Python: >=3.6
Requires-Dist: pandas
Requires-Dist: requests
